[
  {
    "productName": "2.00x0.40",
    "productGroup": "СЕТКА СТАЛЬНАЯ ТКАНАЯ",
    "unit": "м2",
    "ширина": "1000"
  },
  {
    "productName": "5.00x0.70",
    "productGroup": "СЕТКА СТАЛЬНАЯ ТКАНАЯ",
    "unit": "м2",
    "ширина": "1000"
  },
  {
    "productName": "5.00x1.00",
    "productGroup": "СЕТКА СТАЛЬНАЯ ТКАНАЯ",
    "unit": "м2",
    "ширина": "1000"
  },
  {
    "productName": "5.00x1.20",
    "productGroup": "СЕТКА СТАЛЬНАЯ ТКАНАЯ",
    "unit": "м2",
    "ширина": "1000"
  },
  {
    "productName": "10.00x0.80",
    "productGroup": "СЕТКА СТАЛЬНАЯ ТКАНАЯ",
    "unit": "м2",
    "ширина": "1000"
  },
  {
    "productName": "10.00x1.00",
    "productGroup": "СЕТКА СТАЛЬНАЯ ТКАНАЯ",
    "unit": "м2",
    "ширина": "1000"
  },
  {
    "productName": "12.00x0.80 оцинк",
    "productGroup": "СЕТКА СТАЛЬНАЯ ТКАНАЯ",
    "unit": "м2",
    "ширина": "1000"
  },
  {
    "productName": "14.00x0.80",
    "productGroup": "СЕТКА СТАЛЬНАЯ ТКАНАЯ",
    "unit": "м2",
    "ширина": "1000"
  },
  {
    "productName": "14.00x0.80 оцинк",
    "productGroup": "СЕТКА СТАЛЬНАЯ ТКАНАЯ",
    "unit": "м2",
    "ширина": "1000"
  }
]
